README.md
setup.py
sadb/__init__.py
sadb.egg-info/PKG-INFO
sadb.egg-info/SOURCES.txt
sadb.egg-info/dependency_links.txt
sadb.egg-info/entry_points.txt
sadb.egg-info/top_level.txt