Metadata-Version: 1.1
Name: sadb
Version: 0.0.6
Summary: 在多设备时更方便地操作adb
Home-page: https://linroid.com
Author: linroid
Author-email: linroid@gmail.com
License: UNKNOWN
Platform: UNKNOWN
Classifier: Programming Language :: Python :: 2
Classifier: Programming Language :: Python :: 2.7
Classifier: Programming Language :: Python :: 3
Classifier: Programming Language :: Python :: 3.4
Classifier: Programming Language :: Python :: 3.5
Classifier: Programming Language :: Python :: 3.6
